{"clef": 1, "notes": [{"note": 1, "length": 1, "pitch": 1}, {"note": 1, "length": 1, "pitch": 10}, {"note": 1, "length": 1, "pitch": 10}, {"note": 1, "length": 1, "pitch": 2}, {"note": 1, "length": 1, "pitch": 1}, {"note": 1, "length": 1, "pitch": 5}, {"note": 1, "length": 1, "pitch": 8}, {"note": 1, "length": 1, "pitch": 4}, {"note": 1, "length": 1, "pitch": 4}, {"note": 1, "length": 1, "pitch": 4}, {"note": 1, "length": 1, "pitch": 6}, {"note": 1, "length": 1, "pitch": 6}, {"note": 1, "length": 1, "pitch": 12}, {"note": 1, "length": 1, "pitch": 12}, {"note": 1, "length": 1, "pitch": 12}, {"note": 1, "length": 1, "pitch": 12}]}
